mediqbox/abc/__init__.py
mediqbox/abc/abc_component.py
mediqbox/abc/async2sync.py
mediqbox_abc-0.0.4.dist-info/METADATA
mediqbox_abc-0.0.4.dist-info/WHEEL
mediqbox_abc-0.0.4.dist-info/top_level.txt
mediqbox_abc-0.0.4.dist-info/RECORD
