Metadata-Version: 2.1
Name: mediqbox-abc
Version: 0.0.4
Requires-Dist: pydantic
